exf2mbfxml/__init__.py
exf2mbfxml/analysis.py
exf2mbfxml/app.py
exf2mbfxml/exceptions.py
exf2mbfxml/reader.py
exf2mbfxml/result_codes.py
exf2mbfxml/utilities.py
exf2mbfxml/writer.py
exf2mbfxml/zinc.py
exf2mbfxml-0.1.3.dist-info/licenses/LICENSE
exf2mbfxml-0.1.3.dist-info/METADATA
exf2mbfxml-0.1.3.dist-info/WHEEL
exf2mbfxml-0.1.3.dist-info/entry_points.txt
exf2mbfxml-0.1.3.dist-info/top_level.txt
exf2mbfxml-0.1.3.dist-info/RECORD
