Metadata-Version: 2.4
Name: exf2mbfxml
Version: 0.1.3
Summary: Python library for generating MBF XML formatted data from Zinc models written in the EXF format.
Author-email: Hugh Sorby <h.sorby@auckland.ac.nz>
License:                                  Apache License
Keywords: Medical,Physiology,Mesh,Finite Element,Convert,Neuroscience
Classifier: Programming Language :: Python :: 3
Classifier: License :: OSI Approved :: Apache Software License
Classifier: Operating System :: OS Independent
Classifier: Topic :: Scientific/Engineering :: Medical Science Apps.
Requires-Python: >=3.9
License-File: LICENSE
Requires-Dist: cmlibs.utils>=0.6
Requires-Dist: cmlibs.zinc>=4.1
Provides-Extra: test
Requires-Dist: coverage; extra == "test"
Requires-Dist: packaging; extra == "test"
Dynamic: license-file
